thonnycontrib/JuiceMind/__init__.py
thonnycontrib/JuiceMind/res/MCU 2.png
thonnycontrib/JuiceMind/res/MCU.png
thonnycontrib/JuiceMind/res/MCU_selected.png
thonnycontrib/JuiceMind/res/_disabled_MCU 2.png
thonnycontrib/JuiceMind/res/_disabled_MCU.png
thonnycontrib/JuiceMind/res/_disabled_computer 2.png
thonnycontrib/JuiceMind/res/_disabled_computer.png
thonnycontrib/JuiceMind/res/_disabled_debug-run 11.png
thonnycontrib/JuiceMind/res/_disabled_debug-run 12.png
thonnycontrib/JuiceMind/res/_disabled_debug-run 2.png
thonnycontrib/JuiceMind/res/_disabled_debug-run 3.png
thonnycontrib/JuiceMind/res/_disabled_debug-run 4.png
thonnycontrib/JuiceMind/res/_disabled_debug-run 5.png
thonnycontrib/JuiceMind/res/_disabled_debug-run 6.png
thonnycontrib/JuiceMind/res/_disabled_debug-run-cursor 3.png
thonnycontrib/JuiceMind/res/_disabled_debug-run-cursor 4.png
thonnycontrib/JuiceMind/res/_disabled_debug-run-cursor 5.png
thonnycontrib/JuiceMind/res/_disabled_debug-run-cursor 6.png
thonnycontrib/JuiceMind/res/_disabled_debug-run-cursor 9.png
thonnycontrib/JuiceMind/res/_disabled_debug-run-cursor.png
thonnycontrib/JuiceMind/res/_disabled_debug-run-cursor48 2.png
thonnycontrib/JuiceMind/res/_disabled_debug-run-cursor48 3.png
thonnycontrib/JuiceMind/res/_disabled_debug-run-cursor48 7.png
thonnycontrib/JuiceMind/res/_disabled_debug-run-cursor48 8.png
thonnycontrib/JuiceMind/res/_disabled_debug-run-cursor48 9.png
thonnycontrib/JuiceMind/res/_disabled_debug-run-cursor48.png
thonnycontrib/JuiceMind/res/_disabled_debug-run.png
thonnycontrib/JuiceMind/res/_disabled_debug-run48 12.png
thonnycontrib/JuiceMind/res/_disabled_debug-run48 2.png
thonnycontrib/JuiceMind/res/_disabled_debug-run48 3.png
thonnycontrib/JuiceMind/res/_disabled_debug-run48 4.png
thonnycontrib/JuiceMind/res/_disabled_debug-run48 5.png
thonnycontrib/JuiceMind/res/_disabled_debug-run48 6.png
thonnycontrib/JuiceMind/res/_disabled_debug-run48 8.png
thonnycontrib/JuiceMind/res/_disabled_debug-run48.png
thonny_JuiceMind-1.0.0.dist-info/LICENSE
thonny_JuiceMind-1.0.0.dist-info/METADATA
thonny_JuiceMind-1.0.0.dist-info/WHEEL
thonny_JuiceMind-1.0.0.dist-info/top_level.txt
thonny_JuiceMind-1.0.0.dist-info/RECORD
